cunumbers/__init__.py
cunumbers/cunumbers.py
tests/__init__.py
tests/test_cunumbers.py
cu_numbers-2.0.0.dist-info/LICENSE
cu_numbers-2.0.0.dist-info/METADATA
cu_numbers-2.0.0.dist-info/WHEEL
cu_numbers-2.0.0.dist-info/top_level.txt
cu_numbers-2.0.0.dist-info/RECORD
